mproc.py
mproc-0.0.0.1.dist-info/METADATA
mproc-0.0.0.1.dist-info/WHEEL
mproc-0.0.0.1.dist-info/entry_points.txt
mproc-0.0.0.1.dist-info/top_level.txt
mproc-0.0.0.1.dist-info/RECORD
